StatOmics/__init__.py
StatOmics/main.py
StatOmics/r_interface.py
StatOmics/Analysis/__init__.py
StatOmics/Analysis/kruskal_rank_sum.R
StatOmics/Analysis/mannWhitneyU_test.R
StatOmics/Analysis/normality_check_byShapi.R
StatOmics/Analysis/permutation_basedpvalues.R
StatOmics/Analysis/route1function.R
StatOmics/Analysis/run_friedman.R
StatOmics/Analysis/ttest&BH.R
StatOmics/Analysis/variance_check_byLeve.R
StatOmics/Analysis/welcht_test.R
StatOmics/Preprocessing/Filter_fun_by_Pct.R
StatOmics/Preprocessing/Imputation_byNormal.R
StatOmics/Preprocessing/Normalization_bySingleRef.R
StatOmics/Preprocessing/__init__.py
StatOmics/Preprocessing/log2Transf.R
StatOmics/Test/__init__.py
StatOmics/Test/package_test.R
StatOmics/Test/test1.R
StatOmics/Test/test2.R
statomics-0.6.dist-info/METADATA
statomics-0.6.dist-info/WHEEL
statomics-0.6.dist-info/top_level.txt
statomics-0.6.dist-info/RECORD
