Metadata-Version: 2.4
Name: StatOmics
Version: 0.6
Summary: description
Author: Nathan Li
Project-URL: Homepage, https://github.com/nathanxli/StatOmics
Requires-Dist: rpy2
Requires-Dist: pathlib
